{
  "type": "FeatureCollection",
  "features": [
    {
      "type": "Feature",
      "geometry": { "type": "Point", "coordinates": [2.23, 48.91] },
      "properties": {
        "title": "Nanterre – Bidonville algérien",
        "typologie": "Bidonville",
        "periode": "1950-1970",
        "cause": "Urbanisme hygiéniste, politique migratoire",
        "etat": "Logements sociaux",
        "audio": "audio/Bidonville Nanterre.m4a",
        "text": "Dans les années 50 à 70, ce bidonville accueille des milliers d’Algériens venus travailler en France. Il incarne la marginalisation urbaine des migrants. Détruit par souci d’ordre et d’image, il laisse place à des logements sociaux qui ne portent aucune mémoire visible."
      }
    },
    {
      "type": "Feature",
      "geometry": { "type": "Point", "coordinates": [2.51, 48.82] },
      "properties": {
        "title": "Champigny-sur-Marne – Bidonville portugais",
        "typologie": "Bidonville",
        "periode": "1960-1975",
        "cause": "Intégration urbaine, hygiène",
        "etat": "Quartier pavillonnaire",
        "audio": "audio/Bidonville Champigny-sur-Marne.m4a",
        "text": "Ce vaste bidonville, habité par des migrants portugais dans les années 60, illustre l’informalité du logement ouvrier. Sa destruction visait à faire disparaître un symbole de pauvreté. Aujourd’hui, le quartier est résidentiel et n’évoque plus cette histoire."
      }
    },
    {
      "type": "Feature",
      "geometry": { "type": "Point", "coordinates": [2.24, 48.83] },
      "properties": {
        "title": "Boulogne-Billancourt – Usines Renault",
        "typologie": "Site industriel",
        "periode": "1930-1992",
        "cause": "Désindustrialisation, tertiarisation",
        "etat": "Quartiers d’affaires",
        "audio": "audio/Usines Renault.m4a",
        "text": "Lieu emblématique du travail ouvrier et de la production automobile, les usines Renault structuraient la ville et ses habitants. Fermées dans les années 90, elles sont remplacées par des immeubles tertiaires, effaçant l'identité ouvrière du site."
      }
    }
  ]
}
