{
  "type": "FeatureCollection",
  "features": [
    {
      "type": "Feature",
      "geometry": {"type": "Point", "coordinates": [2.23, 48.91]},
      "properties": {
        "title": "Bidonville de Nanterre",
        "category": "Bidonville","1953–1972"
        "actuelement": "Logements sociaux",
        "audio": "https://drive.google.com/file/d/1v2Wri_P0bsAe9IeEa0CICzbKelnm-l2a/view?usp=drive_link",
        "text": "Ensemble de bidonvilles dans  lequel vivaient plus de 10 mille personnes venues majoritairement d'Algérie, mais aussi du Maroc et du Portugal"
      }
    },
    {
      "type": "Feature",
      "geometry": {"type": "Point", "coordinates": [2.51, 48.82]},
      "properties": {
        "title": "Bidonville de Champigny-sur-Marne",
        "typologie": "Bidonville",
        "periode": "1960-1975",
        "cause": "Intégration urbaine, hygiène",
        "etat": "Quartier pavillonnaire",
        "audio": "https://drive.google.com/file/d/1pu2XRF-BCjBq9dKqynFNsWSBUVrVPZvW/view?usp=sharing",
        "text": "Le bidonville de Champigny-sur-Marne, qui a atteint jusqu'à 15 000 habitants dans les années 1960, était le plus grand de France, principalement habité par des immigrés portugais fuyant la misère et la dictature. "
      }
    },
    {
      "type": "Feature",
      "geometry": {"type": "Point", "coordinates": [2.24, 48.83]},
      "properties": {
        "title": "Usines Renault",
        "typologie": "Site industriel",
        "periode": "1930-1992",
        "cause": "Désindustrialisation",
        "etat": "Quartiers tertiaires et résidentiels",
        "audio": "https://drive.google.com/file/d/1WzGebk8NE7g4jxsN9KjEbbzVe48w6Pnn/view?usp=sharing",
        "text": "L'usine Renault de Billancourt a été un symbole de l’implantation du communisme en milieu ouvrier. Elle est le théâtre de nombreux événements importants dans l'histoire sociale et politique de la France, notamment les grèves de 1936 et de Mai 1968."
      }
    }
  ]
}
